mpf_mc-0.57.1.dist-info/RECORD
mpf_mc-0.57.1.dist-info/entry_points.txt
mpf_mc-0.57.1.dist-info/WHEEL
mpf_mc-0.57.1.dist-info/LICENSE
mpf_mc-0.57.1.dist-info/top_level.txt
mpf_mc-0.57.1.dist-info/AUTHORS
mpf_mc-0.57.1.dist-info/METADATA
mpf_mc.libs/libSDL2_mixer-2-2b59a76a.0.so.0.2.2
mpf_mc.libs/libjpeg-43436dd5.so.62.1.0
mpf_mc.libs/libjbig-78348776.so.2.0
mpf_mc.libs/libSDL2_image-2-86e5a413.0.so.0.2.3
mpf_mc.libs/libgmodule-2-ef3ece87.0.so.0.5600.1
mpf_mc.libs/libSDL2-2-8bd4a2ed.0.so.0.14.0
mpf_mc.libs/libgstreamer-1-0d955082.0.so.0.1004.0
mpf_mc.libs/libwebp-3c26a626.so.4.0.2
mpf_mc.libs/libpng15-ce838cd1.so.15.13.0
mpf_mc.libs/libpcre-9513aab5.so.1.2.0
mpf_mc.libs/libtiff-b6eb22fb.so.5.2.0
mpfmc/_version.py
mpfmc/__init__.py
mpfmc/mcconfig.yaml
mpfmc/uix/widget_magic_events.py
mpfmc/uix/window.py
mpfmc/uix/__init__.py
mpfmc/uix/widget.py
mpfmc/uix/slide.py
mpfmc/uix/effects.py
mpfmc/uix/display.py
mpfmc/uix/relative_animation.py
mpfmc/uix/transitions.py
mpfmc/uix/bitmap_font/label_bitmap_font.py
mpfmc/uix/bitmap_font/bitmap_font.pyx
mpfmc/uix/bitmap_font/bitmap_font.cpython-311-x86_64-linux-gnu.so
mpfmc/uix/bitmap_font/bitmap_font.c
mpfmc/uix/bitmap_font/__init__.py
mpfmc/uix/bitmap_font/.gitignore
mpfmc/icons/256x256.png
mpfmc/icons/48x48.png
mpfmc/icons/16x16.png
mpfmc/icons/128x128.png
mpfmc/icons/__init__.py
mpfmc/icons/mpfmc-logo.png
mpfmc/icons/32x32.png
mpfmc/commands/imc.py
mpfmc/commands/__init__.py
mpfmc/commands/mc.py
mpfmc/tests/test_BcpProcessor.py
mpfmc/tests/test_ColorDmd.py
mpfmc/tests/_test_Template.py
mpfmc/tests/test_DisplayMultiple.py
mpfmc/tests/test_DisplayNone.py
mpfmc/tests/test_Fonts.py
mpfmc/tests/test_MpfPluginConfigPlayerValidation.py
mpfmc/tests/DISABLED_test_GStreamer.py
mpfmc/tests/test_AudioDefaultSettings.py
mpfmc/tests/DISABLED_test_Video.py
mpfmc/tests/test_Modes.py
mpfmc/tests/test_Color.py
mpfmc/tests/test_AudioBadBufferSetting.py
mpfmc/tests/test_SlidePlayer.py
mpfmc/tests/test_Assets.py
mpfmc/tests/MpfMcTestCase.py
mpfmc/tests/test_TextInput.py
mpfmc/tests/test_AudioSoundLoop.py
mpfmc/tests/test_Display.py
mpfmc/tests/test_Audio.py
mpfmc/tests/FullMpfMachineTestCase.py
mpfmc/tests/test_Utils.py
