Metadata-Version: 2.1
Name: mpf-mc
Version: 0.57.1
Summary: Mission Pinball Framework Media Controller
Author-email: The Mission Pinball Framework Team <brian@missionpinball.org>
License: MIT
Project-URL: homepage, https://missionpinball.org
Project-URL: support-forum, https://missionpinball.org/community
Keywords: pinball
Classifier: Development Status :: 4 - Beta
Classifier: Intended Audience :: Developers
Classifier: License :: OSI Approved :: MIT License
Classifier: Programming Language :: Python :: 3.8
Classifier: Programming Language :: Python :: 3.9
Classifier: Programming Language :: Python :: 3.10
Classifier: Programming Language :: Python :: 3.11
Classifier: Natural Language :: English
Classifier: Operating System :: MacOS :: MacOS X
Classifier: Operating System :: Microsoft :: Windows
Classifier: Operating System :: POSIX :: Linux
Classifier: Topic :: Artistic Software
Classifier: Topic :: Games/Entertainment :: Arcade
Requires-Python: <3.12,>=3.8
License-File: LICENSE
License-File: AUTHORS
Requires-Dist: mpf >=0.57.0
Requires-Dist: kivy ==2.2.1
Requires-Dist: psutil ==5.9.8
Requires-Dist: Pygments ==2.16.1
Requires-Dist: ffpyplayer ==4.5.1
Requires-Dist: kivy-deps.sdl2 ==0.6.0 ; platform_system == "Windows"
Requires-Dist: kivy-deps.glew ==0.3.1 ; platform_system == "Windows"
Requires-Dist: kivy-deps.gstreamer ==0.3.3 ; platform_system == "Windows"
